axono/__init__.py
axono/core/__init__.py
axono/core/axonolib.cpython-311-x86_64-linux-gnu.so
axono/core/tensor.py
axono/core/operators/__init__.py
axono/core/operators/add.py
axono/core/operators/matmul.py
axono/core/ops/__init__.py
axono/core/ops/relu.py
axono/data/dataloader.py
axono/data/transforms.py
axono/library/axonolib.cpython-311-x86_64-linux-gnu.so
axono/models/container.py
axono/models/sequential.py
axono/models/transformer.py
axono/nn/layers.py
axono/nn/module.py
axono/train/optimizer.py
axono/train/trainer.py
axono/viz/visualizer.py
axono-0.1.0.data/data/axono/library/axonolib.cpython-311-x86_64-linux-gnu.so
axono.libs/libgomp-273d0f96.so.1.0.0
axono-0.1.0.dist-info/METADATA
axono-0.1.0.dist-info/WHEEL
axono-0.1.0.dist-info/top_level.txt
axono-0.1.0.dist-info/RECORD
axono-0.1.0.dist-info/licenses/LICENSE
axono-0.1.0.dist-info/sboms/auditwheel.cdx.json
