Metadata-Version: 2.4
Name: axono
Version: 0.1.0
Summary: Deep learning framework with tensor operations and neural network modules
Author-email: ByteRainTech <offical@byterain.co>, aztice <offical@byterain.co>
License:                                  Apache License
Project-URL: Homepage, https://github.com/ByteRainTech/Axono
Project-URL: Repository, https://github.com/ByteRainTech/Axono
Project-URL: Documentation, https://axono.readthedocs.io
Classifier: Programming Language :: Python :: 3
Classifier: Programming Language :: Python :: 3.8
Classifier: Programming Language :: Python :: 3.9
Classifier: Programming Language :: Python :: 3.10
Classifier: Programming Language :: Python :: 3.11
Classifier: Programming Language :: Python :: 3.12
Classifier: Programming Language :: Python :: 3.13
Requires-Python: >=3.8
License-File: LICENSE
Requires-Dist: numpy
Requires-Dist: pybind11
Dynamic: license-file
